{
  "sprint": "Sprint 20 - Critical Platform Stabilization",
  "verification_timestamp": "2025-10-12T17:11:29.097007",
  "test_results": {
    "cultural_integration": {
      "component": "cultural_integration",
      "test": "missing_method_fix",
      "status": "PASSED",
      "details": "Generated 3 recommendations successfully",
      "error": ""
    },
    "performance_optimization": {
      "component": "performance_optimization",
      "test": "missing_method_fix",
      "status": "PASSED",
      "details": "Calculated trend confidence: 0.340",
      "error": ""
    },
    "redis_config": {
      "component": "redis_config",
      "test": "configuration_added",
      "status": "PASSED",
      "details": "Redis URL configured: redis://localhost:6379",
      "error": ""
    },
    "core_imports": {
      "component": "core_imports",
      "test": "import_app_models_base",
      "status": "PASSED",
      "details": "Successfully imported app.models.base",
      "error": ""
    }
  },
  "summary": {
    "total_components": 4,
    "total_tests": 7,
    "passed_tests": 6,
    "failed_tests": 1,
    "success_rate": 85.71,
    "component_breakdown": {
      "cultural_integration": {
        "passed": 1,
        "failed": 0,
        "tests": [
          {
            "component": "cultural_integration",
            "test": "missing_method_fix",
            "status": "PASSED",
            "details": "Generated 3 recommendations successfully",
            "error": ""
          }
        ]
      },
      "performance_optimization": {
        "passed": 1,
        "failed": 0,
        "tests": [
          {
            "component": "performance_optimization",
            "test": "missing_method_fix",
            "status": "PASSED",
            "details": "Calculated trend confidence: 0.340",
            "error": ""
          }
        ]
      },
      "redis_config": {
        "passed": 1,
        "failed": 0,
        "tests": [
          {
            "component": "redis_config",
            "test": "configuration_added",
            "status": "PASSED",
            "details": "Redis URL configured: redis://localhost:6379",
            "error": ""
          }
        ]
      },
      "core_imports": {
        "passed": 3,
        "failed": 1,
        "tests": [
          {
            "component": "core_imports",
            "test": "import_app_main",
            "status": "FAILED",
            "details": "",
            "error": "Failed to import app.main: cannot import name 'Integration' from 'app.models.integrations' (C:\\Projects\\ma-saas-platform\\backend\\app\\models\\integrations.py)"
          },
          {
            "component": "core_imports",
            "test": "import_app_core_config",
            "status": "PASSED",
            "details": "Successfully imported app.core.config",
            "error": ""
          },
          {
            "component": "core_imports",
            "test": "import_app_core_database",
            "status": "PASSED",
            "details": "Successfully imported app.core.database",
            "error": ""
          },
          {
            "component": "core_imports",
            "test": "import_app_models_base",
            "status": "PASSED",
            "details": "Successfully imported app.models.base",
            "error": ""
          }
        ]
      }
    },
    "overall_status": "FAILED"
  }
}
